smplotlib/__init__.py
smplotlib/demo.py
smplotlib/smplot.mplstyle
smplotlib/test_data/test_array.npy
smplotlib/ttf/AVHersheyComplexHeavy.ttf
smplotlib/ttf/AVHersheyComplexHeavyItalic.ttf
smplotlib/ttf/AVHersheyComplexLight.ttf
smplotlib/ttf/AVHersheyComplexLightItalic.ttf
smplotlib/ttf/AVHersheyComplexMedium.ttf
smplotlib/ttf/AVHersheyComplexMediumItalic.ttf
smplotlib/ttf/AVHersheyDuplexHeavy.ttf
smplotlib/ttf/AVHersheyDuplexHeavyItalic.ttf
smplotlib/ttf/AVHersheyDuplexLight.ttf
smplotlib/ttf/AVHersheyDuplexLightItalic.ttf
smplotlib/ttf/AVHersheyDuplexMedium.ttf
smplotlib/ttf/AVHersheyDuplexMediumItalic.ttf
smplotlib/ttf/AVHersheySimplexHeavy.ttf
smplotlib/ttf/AVHersheySimplexHeavyItalic.ttf
smplotlib/ttf/AVHersheySimplexLight.ttf
smplotlib/ttf/AVHersheySimplexLightItalic.ttf
smplotlib/ttf/AVHersheySimplexMedium.ttf
smplotlib/ttf/AVHersheySimplexMediumItalic.ttf
smplotlib-1.0.0.dist-info/licenses/LICENSE
smplotlib-1.0.0.dist-info/METADATA
smplotlib-1.0.0.dist-info/WHEEL
smplotlib-1.0.0.dist-info/top_level.txt
smplotlib-1.0.0.dist-info/RECORD
