Metadata-Version: 2.4
Name: smplotlib
Version: 1.0.0
Summary: Matplotlib template for SuperMongo style
Author-email: Jiaxuan Li <jiaxuanl@princeton.edu>
Project-URL: Homepage, https://github.com/AstroJacobLi/smplotlib
Project-URL: Bug Tracker, https://github.com/AstroJacobLi/smplotlib/issues
Classifier: Programming Language :: Python :: 3
Classifier: License :: OSI Approved :: MIT License
Classifier: Operating System :: OS Independent
Requires-Python: >=3.7
License-File: LICENSE
Dynamic: license-file
